sparkhub/__init__.py
sparkhub/_version.py
sparkhub/cloud_utils.py
sparkhub/gcloud.py
sparkhub/gcp.py
sparkhub/hadoopio.py
sparkhub/hailrunner.py
sparkhub/slackconnector.py
sparkhub/submit.py
sparkhub2-0.4.0.dist-info/LICENSE.md
sparkhub2-0.4.0.dist-info/METADATA
sparkhub2-0.4.0.dist-info/WHEEL
sparkhub2-0.4.0.dist-info/entry_points.txt
sparkhub2-0.4.0.dist-info/top_level.txt
sparkhub2-0.4.0.dist-info/RECORD
