Metadata-Version: 2.1
Name: sparkhub2
Version: 0.4.0
Summary: Cloud utilities for running Hail systematically.
Home-page: https://github.com/tjsinghlab/sparkhub
Author: Singh Lab
Author-email: singhlab@nygenome.org
License: MIT License
Requires-Python: >=3.7
License-File: LICENSE.md
Requires-Dist: versioneer ==0.29
Requires-Dist: loguru
Requires-Dist: hail >=0.2.45
Requires-Dist: slack-sdk
